python_boilerplate/__init__.py
python_boilerplate/cli.py
python_boilerplate/core.py
bryn_python_boilerplate-0.1.4.dist-info/LICENSE
bryn_python_boilerplate-0.1.4.dist-info/METADATA
bryn_python_boilerplate-0.1.4.dist-info/WHEEL
bryn_python_boilerplate-0.1.4.dist-info/entry_points.txt
bryn_python_boilerplate-0.1.4.dist-info/top_level.txt
bryn_python_boilerplate-0.1.4.dist-info/RECORD
