Metadata-Version: 2.1
Name: bryn_python_boilerplate
Version: 0.1.4
Summary: Python Boilerplate contains all the boilerplate you need to create a Python package.
Author-email: Bryn Pickering <17178478+brynpickering@users.noreply.github.com>
License: MIT
Project-URL: repository, https://github.com/brynpickering/python_boilerplate
Project-URL: documentation, https://brynpickering.github.io/python_boilerplate
Project-URL: changelog, https://github.com/brynpickering/python_boilerplate/blob/main/CHANGELOG.md
Keywords: python_boilerplate
Classifier: Development Status :: 2 - Pre-Alpha
Classifier: Intended Audience :: Developers
Classifier: License :: OSI Approved :: MIT License
Classifier: Natural Language :: English
Classifier: Programming Language :: Python :: 3
Requires-Python: >=3.8
License-File: LICENSE
Requires-Dist: numpy
Requires-Dist: pandas
Provides-Extra: dev
Requires-Dist: jupyter <2 ; extra == 'dev'
Requires-Dist: mike <3,>=2 ; extra == 'dev'
Requires-Dist: mkdocs <2 ; extra == 'dev'
Requires-Dist: mkdocs-material <10,>=9.4 ; extra == 'dev'
Requires-Dist: mkdocs-click <0.7 ; extra == 'dev'
Requires-Dist: mkdocs-jupyter <0.25 ; extra == 'dev'
Requires-Dist: mkdocstrings-python <2 ; extra == 'dev'
Requires-Dist: nbmake <2 ; extra == 'dev'
Requires-Dist: pre-commit <4 ; extra == 'dev'
Requires-Dist: pytest <9,>=8 ; extra == 'dev'
Requires-Dist: pytest-cov <5 ; extra == 'dev'
Requires-Dist: pytest-mock <4 ; extra == 'dev'
Requires-Dist: pytest-timeout <3 ; extra == 'dev'
Requires-Dist: pytest-xdist <4 ; extra == 'dev'
